pyrobbot/.ruff_cache/.gitignore
pyrobbot/.ruff_cache/CACHEDIR.TAG
pyrobbot/.ruff_cache/content/3953151933896433786
pyrobbot/__init__.py
pyrobbot/__main__.py
pyrobbot/app/.streamlit/config.toml
pyrobbot/app/__init__.py
pyrobbot/app/app.py
pyrobbot/app/app_page_templates.py
pyrobbot/app/app_utils.py
pyrobbot/app/data/assistant_avatar.png
pyrobbot/app/data/powered-by-openai-badge-outlined-on-dark.svg
pyrobbot/app/data/powered-by-openai-badge-outlined-on-light.svg
pyrobbot/app/data/success.wav
pyrobbot/app/data/user_avatar.png
pyrobbot/app/data/warning.wav
pyrobbot/app/multipage.py
pyrobbot/argparse_wrapper.py
pyrobbot/chat.py
pyrobbot/chat_configs.py
pyrobbot/chat_context.py
pyrobbot/command_definitions.py
pyrobbot/embeddings_database.py
pyrobbot/general_utils.py
pyrobbot/internet_utils.py
pyrobbot/openai_utils.py
pyrobbot/sst_and_tts.py
pyrobbot/tokens.py
pyrobbot/voice_chat.py
pyrobbot-0.7.6.dist-info/LICENSE.md
pyrobbot-0.7.6.dist-info/METADATA
pyrobbot-0.7.6.dist-info/WHEEL
pyrobbot-0.7.6.dist-info/entry_points.txt
pyrobbot-0.7.6.dist-info/RECORD
