Metadata-Version: 2.1
Name: pyrobbot
Version: 0.7.6
Summary: Chat with GPT LLMs over voice, text or both. With access to the internet.Powered by OpenAI.
License: MIT
Author: Paulo V C Medeiros
Author-email: impaulov@gmail.com
Requires-Python: >=3.9, !=2.7.*, !=3.0.*, !=3.1.*, !=3.2.*, !=3.3.*, !=3.4.*, !=3.5.*, !=3.6.*, !=3.7.*, !=3.8.*
Classifier: License :: OSI Approved :: MIT License
Classifier: Programming Language :: Python :: 3
Classifier: Programming Language :: Python :: 3.9
Classifier: Programming Language :: Python :: 3.10
Classifier: Programming Language :: Python :: 3.11
Classifier: Programming Language :: Python :: 3.12
Requires-Dist: audio-recorder-streamlit (>=0.0.8,<0.0.9)
Requires-Dist: beautifulsoup4 (>=4.12.3,<5.0.0)
Requires-Dist: chime (>=0.7.0,<0.8.0)
Requires-Dist: duckduckgo-search (>=5.0,<6.0)
Requires-Dist: gtts (>=2.5.1,<3.0.0)
Requires-Dist: httpx (>=0.26.0,<0.27.0)
Requires-Dist: ipinfo (>=5.0.1,<6.0.0)
Requires-Dist: loguru (>=0.7.2,<0.8.0)
Requires-Dist: matplotlib (>=3.8.0,<4.0.0)
Requires-Dist: numpy (>=1.26.1,<2.0.0)
Requires-Dist: openai (>=1.13.3,<2.0.0)
Requires-Dist: pandas (>=2.2.0,<3.0.0)
Requires-Dist: pillow (>=10.2.0,<11.0.0)
Requires-Dist: plotly (>=5.18.0,<6.0.0)
Requires-Dist: pydantic (>=2.6.1,<3.0.0)
Requires-Dist: pydub (>=0.25.1,<0.26.0)
Requires-Dist: pygame (>=2.5.2,<3.0.0)
Requires-Dist: scikit-learn (>=1.3.2,<2.0.0)
Requires-Dist: scipy (>=1.11.3,<2.0.0)
Requires-Dist: setuptools (>=68.2.2,<69.0.0)
Requires-Dist: sounddevice (>=0.4.6,<0.5.0)
Requires-Dist: soundfile (>=0.12.1,<0.13.0)
Requires-Dist: speechrecognition (>=3.10.0,<4.0.0)
Requires-Dist: streamlit (>=1.31.1,<2.0.0)
Requires-Dist: streamlit-mic-recorder (>=0.0.4,<0.0.5)
Requires-Dist: streamlit-webrtc (>=0.47.1,<0.48.0)
Requires-Dist: tiktoken (>=0.6.0,<0.7.0)
Requires-Dist: twilio (>=9.0.0,<10.0.0)
Requires-Dist: tzlocal (>=5.2,<6.0)
Requires-Dist: unidecode (>=1.3.7,<2.0.0)
Requires-Dist: webrtcvad-wheels (>=2.0.11.post1,<3.0.0)
